Workbook

Sheet Listas Validadas
B2: Tipo | D2: Cat. Ingreso | F2: Cat. Egreso | H2: Mes
B3: Ingreso | D3: Sueldo | F3: Servicios | H3: Enero
B4: Egreso | D4: Negocios | F4: Gastos | H4: Febrero
D5: Otros | F5: Prestamos | H5: Marzo
F6: Ahorros | H6: Abril
H7: Mayo
H8: Junio
H9: Julio
H10: Agosto
H11: Septiembre
H12: Octubre
H13: Noviembre
H14: Diciembre

Sheet Registro Ingreso Egreso
A1: Manejo del dinero de Jefferson
A2: Fecha | B2: Mes | C2: Tipo | D2: Categoria | E2: Descripcion | F2: Presupuesto | G2: Monto | I2: Categoria | J2: Monto | K2: Tipo
A3: 46025 | B3: =IF(DINEROJEFF[[#This Row],[Fecha ]]<>"",TEXT(DINEROJEFF[[#This Row],[Fecha ]],"MMMM"),"") -> enero | C3: Ingreso | D3: Sueldo | E3: Sueldo del mes | F3: 550 | G3: 545.6 | I3: {=IFERROR(_xlfn.UNIQUE(_xlfn._xlws.FILTER(DINEROJEFF[Categoria],(DINEROJEFF[Mes]=$B$3))),"")} -> Sueldo | J3: =SUMIFS(DINEROJEFF[Monto],DINEROJEFF[Mes],Informe!$B$3,DINEROJEFF[Categoria],I3) *IF(K3="Ingreso",1,-1) -> 545.6 | K3: =IFERROR(_xlfn.XLOOKUP(I3,DINEROJEFF[Categoria],DINEROJEFF[Tipo]),"") -> Ingreso
A4: 46027 | B4: =IF(DINEROJEFF[[#This Row],[Fecha ]]<>"",TEXT(DINEROJEFF[[#This Row],[Fecha ]],"MMMM"),"") -> enero | C4: Egreso | D4: Servicios | E4: Alimentacion | F4: 150 | G4: 0 | I4: Servicios | J4: =SUMIFS(DINEROJEFF[Monto],DINEROJEFF[Mes],Informe!$B$3,DINEROJEFF[Categoria],I4) *IF(K4="Ingreso",1,-1) -> -7.5 | K4: =IFERROR(_xlfn.XLOOKUP(I4,DINEROJEFF[Categoria],DINEROJEFF[Tipo]),"") -> Egreso
A5: 45664 | B5: =IF(DINEROJEFF[[#This Row],[Fecha ]]<>"",TEXT(DINEROJEFF[[#This Row],[Fecha ]],"MMMM"),"") -> enero | C5: Egreso | D5: Gastos | E5: Servico de Coris del Ecuador S.A | F5: 0 | G5: 37 | I5: Gastos | J5: =SUMIFS(DINEROJEFF[Monto],DINEROJEFF[Mes],Informe!$B$3,DINEROJEFF[Categoria],I5) *IF(K5="Ingreso",1,-1) -> -47 | K5: =IFERROR(_xlfn.XLOOKUP(I5,DINEROJEFF[Categoria],DINEROJEFF[Tipo]),"") -> Egreso
A6: 45667 | B6: =IF(DINEROJEFF[[#This Row],[Fecha ]]<>"",TEXT(DINEROJEFF[[#This Row],[Fecha ]],"MMMM"),"") -> enero | C6: Ingreso | D6: Otros | E6: Cobro prestamo | F6: 50 | G6: 50 | I6: Otros | J6: =SUMIFS(DINEROJEFF[Monto],DINEROJEFF[Mes],Informe!$B$3,DINEROJEFF[Categoria],I6) *IF(K6="Ingreso",1,-1) -> 50 | K6: =IFERROR(_xlfn.XLOOKUP(I6,DINEROJEFF[Categoria],DINEROJEFF[Tipo]),"") -> Ingreso
A7: 45676 | B7: =IF(DINEROJEFF[[#This Row],[Fecha ]]<>"",TEXT(DINEROJEFF[[#This Row],[Fecha ]],"MMMM"),"") -> enero | C7: Egreso | D7: Gastos | E7: Comida del perro | F7: 15 | G7: 10 | J7: =SUMIFS(DINEROJEFF[Monto],DINEROJEFF[Mes],Informe!$B$3,DINEROJEFF[Categoria],I7) *IF(K7="Ingreso",1,-1) -> 0 | K7: =IFERROR(_xlfn.XLOOKUP(I7,DINEROJEFF[Categoria],DINEROJEFF[Tipo]),"")
A8: 46047 | B8: =IF(DINEROJEFF[[#This Row],[Fecha ]]<>"",TEXT(DINEROJEFF[[#This Row],[Fecha ]],"MMMM"),"") -> enero | C8: Egreso | D8: Servicios | E8: Recibo de internet | F8: 20 | G8: 0 | J8: =SUMIFS(DINEROJEFF[Monto],DINEROJEFF[Mes],Informe!$B$3,DINEROJEFF[Categoria],I8) *IF(K8="Ingreso",1,-1) -> 0 | K8: =IFERROR(_xlfn.XLOOKUP(I8,DINEROJEFF[Categoria],DINEROJEFF[Tipo]),"")
A9: 38742 | B9: =IF(DINEROJEFF[[#This Row],[Fecha ]]<>"",TEXT(DINEROJEFF[[#This Row],[Fecha ]],"MMMM"),"") -> enero | C9: Egreso | D9: Servicios | E9: Recibo de youtube | F9: 7.5 | G9: 7.5 | J9: =SUMIFS(DINEROJEFF[Monto],DINEROJEFF[Mes],Informe!$B$3,DINEROJEFF[Categoria],I9) *IF(K9="Ingreso",1,-1) -> 0 | K9: =IFERROR(_xlfn.XLOOKUP(I9,DINEROJEFF[Categoria],DINEROJEFF[Tipo]),"")
I10: Total | J10: =+SUM(J3:J9) -> 541.1 | K10: =+SUM(K3:K9) -> 0

Sheet Informe
B2: Selecciona el Mes
B3: Enero | F3: Saldo | H3: =+B6-F6 -> 541.1
B5: INGRESOS TOTALES | F5: EGRESOS TOTALES
B6: =+SUMIFS(DINEROJEFF[Monto],DINEROJEFF[Tipo],"Ingreso",DINEROJEFF[Mes],B3) -> 595.6 | F6: =+SUMIFS(DINEROJEFF[Monto],DINEROJEFF[Tipo],"Egreso",DINEROJEFF[Mes],B3) -> 54.5
C7: Ppto | D7: =+SUMIFS(DINEROJEFF[Presupuesto],DINEROJEFF[Tipo],"Ingreso",DINEROJEFF[Mes],B3) -> 600 | G7: Ppto | H7: =+SUMIFS(DINEROJEFF[Presupuesto],DINEROJEFF[Tipo],"Egreso",DINEROJEFF[Mes],B3) -> 192.5
C8: Dif | D8: =+B6-D7 -> -4.4 | G8: Dif | H8: =+F6-H7 -> -138
B10: Resumen Ingresos | F10: Resumen Egresos | J10: Servicios | N10: Gastos | R10: Prestamos
B11: Categoria | C11: Presupuesto | D11: Monto | F11: Categoria | G11: Presupuesto | H11: Monto | J11: Concepto | K11: Presupuesto | L11: Monto | N11: Concepto | O11: Presupuesto | P11: Monto | R11: Concepto | S11: Presupuesto | T11: Monto
B12: {=IFERROR(_xlfn.UNIQUE(_xlfn._xlws.FILTER(DINEROJEFF[Categoria],(DINEROJEFF[Mes]=$B$3)*(DINEROJEFF[Tipo]="Ingreso"))),"")} -> Sueldo | C12: =+SUMIFS(DINEROJEFF[Presupuesto],DINEROJEFF[Mes],$B$3,DINEROJEFF[Categoria],B12) -> 550 | D12: =+SUMIFS(DINEROJEFF[Monto],DINEROJEFF[Mes],$B$3,DINEROJEFF[Categoria],B12) -> 545.6 | F12: {=IFERROR(_xlfn.UNIQUE(_xlfn._xlws.FILTER(DINEROJEFF[Categoria],(DINEROJEFF[Mes]=$B$3)*(DINEROJEFF[Tipo]="Egreso"))),"")} -> Servicios | G12: =+SUMIFS(DINEROJEFF[Presupuesto],DINEROJEFF[Mes],$B$3,DINEROJEFF[Categoria],F12) -> 177.5 | H12: =+SUMIFS(DINEROJEFF[Monto],DINEROJEFF[Mes],$B$3,DINEROJEFF[Categoria],F12) -> 7.5 | J12: {=IFERROR(_xlfn.UNIQUE(_xlfn._xlws.FILTER(DINEROJEFF[[Descripcion ]],(DINEROJEFF[Mes]=$B$3)*(DINEROJEFF[Categoria]=J10))),"")} -> Alimentacion | K12: =+SUMIFS(DINEROJEFF[Presupuesto],DINEROJEFF[Mes],$B$3,DINEROJEFF[[Descripcion ]],J12) -> 150 | L12: =+SUMIFS(DINEROJEFF[Monto],DINEROJEFF[Mes],$B$3,DINEROJEFF[[Descripcion ]],J12) -> 0 | N12: {=IFERROR(_xlfn.UNIQUE(_xlfn._xlws.FILTER(DINEROJEFF[[Descripcion ]],(DINEROJEFF[Mes]=$B$3)*(DINEROJEFF[Categoria]=N10))),"")} -> Servico de Coris del Ecuador S.A | O12: =+SUMIFS(DINEROJEFF[Presupuesto],DINEROJEFF[Mes],$B$3,DINEROJEFF[[Descripcion ]],N12) -> 0 | P12: =+SUMIFS(DINEROJEFF[Monto],DINEROJEFF[Mes],$B$3,DINEROJEFF[[Descripcion ]],N12) -> 37 | R12: {=IFERROR(_xlfn.UNIQUE(_xlfn._xlws.FILTER(DINEROJEFF[[Descripcion ]],(DINEROJEFF[Mes]=$B$3)*(DINEROJEFF[Categoria]=R10))),"")} | S12: =+SUMIFS(DINEROJEFF[Presupuesto],DINEROJEFF[Mes],$B$3,DINEROJEFF[[Descripcion ]],R12) -> 0 | T12: =+SUMIFS(DINEROJEFF[Monto],DINEROJEFF[Mes],$B$3,DINEROJEFF[[Descripcion ]],R12) -> 0
B13: Otros | C13: =+SUMIFS(DINEROJEFF[Presupuesto],DINEROJEFF[Mes],$B$3,DINEROJEFF[Categoria],B13) -> 50 | D13: =+SUMIFS(DINEROJEFF[Monto],DINEROJEFF[Mes],$B$3,DINEROJEFF[Categoria],B13) -> 50 | F13: Gastos | G13: =+SUMIFS(DINEROJEFF[Presupuesto],DINEROJEFF[Mes],$B$3,DINEROJEFF[Categoria],F13) -> 15 | H13: =+SUMIFS(DINEROJEFF[Monto],DINEROJEFF[Mes],$B$3,DINEROJEFF[Categoria],F13) -> 47 | J13: Recibo de internet | K13: =+SUMIFS(DINEROJEFF[Presupuesto],DINEROJEFF[Mes],$B$3,DINEROJEFF[[Descripcion ]],J13) -> 20 | L13: =+SUMIFS(DINEROJEFF[Monto],DINEROJEFF[Mes],$B$3,DINEROJEFF[[Descripcion ]],J13) -> 0 | N13: Comida del perro | O13: =+SUMIFS(DINEROJEFF[Presupuesto],DINEROJEFF[Mes],$B$3,DINEROJEFF[[Descripcion ]],N13) -> 15 | P13: =+SUMIFS(DINEROJEFF[Monto],DINEROJEFF[Mes],$B$3,DINEROJEFF[[Descripcion ]],N13) -> 10 | S13: =+SUMIFS(DINEROJEFF[Presupuesto],DINEROJEFF[Mes],$B$3,DINEROJEFF[[Descripcion ]],R13) -> 0 | T13: =+SUMIFS(DINEROJEFF[Monto],DINEROJEFF[Mes],$B$3,DINEROJEFF[[Descripcion ]],R13) -> 0
C14: =+SUMIFS(DINEROJEFF[Presupuesto],DINEROJEFF[Mes],$B$3,DINEROJEFF[Categoria],B14) -> 0 | D14: =+SUMIFS(DINEROJEFF[Monto],DINEROJEFF[Mes],$B$3,DINEROJEFF[Categoria],B14) -> 0 | G14: =+SUMIFS(DINEROJEFF[Presupuesto],DINEROJEFF[Mes],$B$3,DINEROJEFF[Categoria],F14) -> 0 | H14: =+SUMIFS(DINEROJEFF[Monto],DINEROJEFF[Mes],$B$3,DINEROJEFF[Categoria],F14) -> 0 | J14: Recibo de youtube | K14: =+SUMIFS(DINEROJEFF[Presupuesto],DINEROJEFF[Mes],$B$3,DINEROJEFF[[Descripcion ]],J14) -> 7.5 | L14: =+SUMIFS(DINEROJEFF[Monto],DINEROJEFF[Mes],$B$3,DINEROJEFF[[Descripcion ]],J14) -> 7.5 | O14: =+SUMIFS(DINEROJEFF[Presupuesto],DINEROJEFF[Mes],$B$3,DINEROJEFF[[Descripcion ]],N14) -> 0 | P14: =+SUMIFS(DINEROJEFF[Monto],DINEROJEFF[Mes],$B$3,DINEROJEFF[[Descripcion ]],N14) -> 0 | S14: =+SUMIFS(DINEROJEFF[Presupuesto],DINEROJEFF[Mes],$B$3,DINEROJEFF[[Descripcion ]],R14) -> 0 | T14: =+SUMIFS(DINEROJEFF[Monto],DINEROJEFF[Mes],$B$3,DINEROJEFF[[Descripcion ]],R14) -> 0
C15: =+SUMIFS(DINEROJEFF[Presupuesto],DINEROJEFF[Mes],$B$3,DINEROJEFF[Categoria],B15) -> 0 | D15: =+SUMIFS(DINEROJEFF[Monto],DINEROJEFF[Mes],$B$3,DINEROJEFF[Categoria],B15) -> 0 | G15: =+SUMIFS(DINEROJEFF[Presupuesto],DINEROJEFF[Mes],$B$3,DINEROJEFF[Categoria],F15) -> 0 | H15: =+SUMIFS(DINEROJEFF[Monto],DINEROJEFF[Mes],$B$3,DINEROJEFF[Categoria],F15) -> 0 | K15: =+SUMIFS(DINEROJEFF[Presupuesto],DINEROJEFF[Mes],$B$3,DINEROJEFF[[Descripcion ]],J15) -> 0 | L15: =+SUMIFS(DINEROJEFF[Monto],DINEROJEFF[Mes],$B$3,DINEROJEFF[[Descripcion ]],J15) -> 0 | O15: =+SUMIFS(DINEROJEFF[Presupuesto],DINEROJEFF[Mes],$B$3,DINEROJEFF[[Descripcion ]],N15) -> 0 | P15: =+SUMIFS(DINEROJEFF[Monto],DINEROJEFF[Mes],$B$3,DINEROJEFF[[Descripcion ]],N15) -> 0 | S15: =+SUMIFS(DINEROJEFF[Presupuesto],DINEROJEFF[Mes],$B$3,DINEROJEFF[[Descripcion ]],R15) -> 0 | T15: =+SUMIFS(DINEROJEFF[Monto],DINEROJEFF[Mes],$B$3,DINEROJEFF[[Descripcion ]],R15) -> 0
C16: =+SUMIFS(DINEROJEFF[Presupuesto],DINEROJEFF[Mes],$B$3,DINEROJEFF[Categoria],B16) -> 0 | D16: =+SUMIFS(DINEROJEFF[Monto],DINEROJEFF[Mes],$B$3,DINEROJEFF[Categoria],B16) -> 0 | G16: =+SUMIFS(DINEROJEFF[Presupuesto],DINEROJEFF[Mes],$B$3,DINEROJEFF[Categoria],F16) -> 0 | H16: =+SUMIFS(DINEROJEFF[Monto],DINEROJEFF[Mes],$B$3,DINEROJEFF[Categoria],F16) -> 0 | K16: =+SUMIFS(DINEROJEFF[Presupuesto],DINEROJEFF[Mes],$B$3,DINEROJEFF[[Descripcion ]],J16) -> 0 | L16: =+SUMIFS(DINEROJEFF[Monto],DINEROJEFF[Mes],$B$3,DINEROJEFF[[Descripcion ]],J16) -> 0 | O16: =+SUMIFS(DINEROJEFF[Presupuesto],DINEROJEFF[Mes],$B$3,DINEROJEFF[[Descripcion ]],N16) -> 0 | P16: =+SUMIFS(DINEROJEFF[Monto],DINEROJEFF[Mes],$B$3,DINEROJEFF[[Descripcion ]],N16) -> 0 | S16: =+SUMIFS(DINEROJEFF[Presupuesto],DINEROJEFF[Mes],$B$3,DINEROJEFF[[Descripcion ]],R16) -> 0 | T16: =+SUMIFS(DINEROJEFF[Monto],DINEROJEFF[Mes],$B$3,DINEROJEFF[[Descripcion ]],R16) -> 0
B17: Total | C17: =+SUM(C12:C16) -> 600 | D17: =+SUM(D12:D16) -> 595.6 | F17: Total | G17: =+SUM(G12:G16) -> 192.5 | H17: =+SUM(H12:H16) -> 54.5 | K17: =+SUMIFS(DINEROJEFF[Presupuesto],DINEROJEFF[Mes],$B$3,DINEROJEFF[[Descripcion ]],J17) -> 0 | L17: =+SUMIFS(DINEROJEFF[Monto],DINEROJEFF[Mes],$B$3,DINEROJEFF[[Descripcion ]],J17) -> 0 | O17: =+SUMIFS(DINEROJEFF[Presupuesto],DINEROJEFF[Mes],$B$3,DINEROJEFF[[Descripcion ]],N17) -> 0 | P17: =+SUMIFS(DINEROJEFF[Monto],DINEROJEFF[Mes],$B$3,DINEROJEFF[[Descripcion ]],N17) -> 0 | S17: =+SUMIFS(DINEROJEFF[Presupuesto],DINEROJEFF[Mes],$B$3,DINEROJEFF[[Descripcion ]],R17) -> 0 | T17: =+SUMIFS(DINEROJEFF[Monto],DINEROJEFF[Mes],$B$3,DINEROJEFF[[Descripcion ]],R17) -> 0
K18: =+SUMIFS(DINEROJEFF[Presupuesto],DINEROJEFF[Mes],$B$3,DINEROJEFF[[Descripcion ]],J18) -> 0 | L18: =+SUMIFS(DINEROJEFF[Monto],DINEROJEFF[Mes],$B$3,DINEROJEFF[[Descripcion ]],J18) -> 0 | O18: =+SUMIFS(DINEROJEFF[Presupuesto],DINEROJEFF[Mes],$B$3,DINEROJEFF[[Descripcion ]],N18) -> 0 | P18: =+SUMIFS(DINEROJEFF[Monto],DINEROJEFF[Mes],$B$3,DINEROJEFF[[Descripcion ]],N18) -> 0 | R18: Total | S18: =+SUM(S12:S17) -> 0 | T18: =+SUM(T12:T17) -> 0
K19: =+SUMIFS(DINEROJEFF[Presupuesto],DINEROJEFF[Mes],$B$3,DINEROJEFF[[Descripcion ]],J19) -> 0 | L19: =+SUMIFS(DINEROJEFF[Monto],DINEROJEFF[Mes],$B$3,DINEROJEFF[[Descripcion ]],J19) -> 0 | O19: =+SUMIFS(DINEROJEFF[Presupuesto],DINEROJEFF[Mes],$B$3,DINEROJEFF[[Descripcion ]],N19) -> 0 | P19: =+SUMIFS(DINEROJEFF[Monto],DINEROJEFF[Mes],$B$3,DINEROJEFF[[Descripcion ]],N19) -> 0
K20: =+SUMIFS(DINEROJEFF[Presupuesto],DINEROJEFF[Mes],$B$3,DINEROJEFF[[Descripcion ]],J20) -> 0 | L20: =+SUMIFS(DINEROJEFF[Monto],DINEROJEFF[Mes],$B$3,DINEROJEFF[[Descripcion ]],J20) -> 0 | O20: =+SUMIFS(DINEROJEFF[Presupuesto],DINEROJEFF[Mes],$B$3,DINEROJEFF[[Descripcion ]],N20) -> 0 | P20: =+SUMIFS(DINEROJEFF[Monto],DINEROJEFF[Mes],$B$3,DINEROJEFF[[Descripcion ]],N20) -> 0 | R20: Ahorros
K21: =+SUMIFS(DINEROJEFF[Presupuesto],DINEROJEFF[Mes],$B$3,DINEROJEFF[[Descripcion ]],J21) -> 0 | L21: =+SUMIFS(DINEROJEFF[Monto],DINEROJEFF[Mes],$B$3,DINEROJEFF[[Descripcion ]],J21) -> 0 | O21: =+SUMIFS(DINEROJEFF[Presupuesto],DINEROJEFF[Mes],$B$3,DINEROJEFF[[Descripcion ]],N21) -> 0 | P21: =+SUMIFS(DINEROJEFF[Monto],DINEROJEFF[Mes],$B$3,DINEROJEFF[[Descripcion ]],N21) -> 0 | R21: Concepto | S21: Presupuesto | T21: Monto
K22: =+SUMIFS(DINEROJEFF[Presupuesto],DINEROJEFF[Mes],$B$3,DINEROJEFF[[Descripcion ]],J22) -> 0 | L22: =+SUMIFS(DINEROJEFF[Monto],DINEROJEFF[Mes],$B$3,DINEROJEFF[[Descripcion ]],J22) -> 0 | O22: =+SUMIFS(DINEROJEFF[Presupuesto],DINEROJEFF[Mes],$B$3,DINEROJEFF[[Descripcion ]],N22) -> 0 | P22: =+SUMIFS(DINEROJEFF[Monto],DINEROJEFF[Mes],$B$3,DINEROJEFF[[Descripcion ]],N22) -> 0 | R22: {=IFERROR(_xlfn.UNIQUE(_xlfn._xlws.FILTER(DINEROJEFF[[Descripcion ]],(DINEROJEFF[Mes]=$B$3)*(DINEROJEFF[Categoria]=R20))),"")} | S22: =+SUMIFS(DINEROJEFF[Presupuesto],DINEROJEFF[Mes],$B$3,DINEROJEFF[[Descripcion ]],R22) -> 0 | T22: =+SUMIFS(DINEROJEFF[Monto],DINEROJEFF[Mes],$B$3,DINEROJEFF[[Descripcion ]],R22) -> 0
K23: =+SUMIFS(DINEROJEFF[Presupuesto],DINEROJEFF[Mes],$B$3,DINEROJEFF[[Descripcion ]],J23) -> 0 | L23: =+SUMIFS(DINEROJEFF[Monto],DINEROJEFF[Mes],$B$3,DINEROJEFF[[Descripcion ]],J23) -> 0 | O23: =+SUMIFS(DINEROJEFF[Presupuesto],DINEROJEFF[Mes],$B$3,DINEROJEFF[[Descripcion ]],N23) -> 0 | P23: =+SUMIFS(DINEROJEFF[Monto],DINEROJEFF[Mes],$B$3,DINEROJEFF[[Descripcion ]],N23) -> 0 | S23: =+SUMIFS(DINEROJEFF[Presupuesto],DINEROJEFF[Mes],$B$3,DINEROJEFF[[Descripcion ]],R23) -> 0 | T23: =+SUMIFS(DINEROJEFF[Monto],DINEROJEFF[Mes],$B$3,DINEROJEFF[[Descripcion ]],R23) -> 0
K24: =+SUMIFS(DINEROJEFF[Presupuesto],DINEROJEFF[Mes],$B$3,DINEROJEFF[[Descripcion ]],J24) -> 0 | L24: =+SUMIFS(DINEROJEFF[Monto],DINEROJEFF[Mes],$B$3,DINEROJEFF[[Descripcion ]],J24) -> 0 | O24: =+SUMIFS(DINEROJEFF[Presupuesto],DINEROJEFF[Mes],$B$3,DINEROJEFF[[Descripcion ]],N24) -> 0 | P24: =+SUMIFS(DINEROJEFF[Monto],DINEROJEFF[Mes],$B$3,DINEROJEFF[[Descripcion ]],N24) -> 0 | S24: =+SUMIFS(DINEROJEFF[Presupuesto],DINEROJEFF[Mes],$B$3,DINEROJEFF[[Descripcion ]],R24) -> 0 | T24: =+SUMIFS(DINEROJEFF[Monto],DINEROJEFF[Mes],$B$3,DINEROJEFF[[Descripcion ]],R24) -> 0
K25: =+SUMIFS(DINEROJEFF[Presupuesto],DINEROJEFF[Mes],$B$3,DINEROJEFF[[Descripcion ]],J25) -> 0 | L25: =+SUMIFS(DINEROJEFF[Monto],DINEROJEFF[Mes],$B$3,DINEROJEFF[[Descripcion ]],J25) -> 0 | O25: =+SUMIFS(DINEROJEFF[Presupuesto],DINEROJEFF[Mes],$B$3,DINEROJEFF[[Descripcion ]],N25) -> 0 | P25: =+SUMIFS(DINEROJEFF[Monto],DINEROJEFF[Mes],$B$3,DINEROJEFF[[Descripcion ]],N25) -> 0 | S25: =+SUMIFS(DINEROJEFF[Presupuesto],DINEROJEFF[Mes],$B$3,DINEROJEFF[[Descripcion ]],R25) -> 0 | T25: =+SUMIFS(DINEROJEFF[Monto],DINEROJEFF[Mes],$B$3,DINEROJEFF[[Descripcion ]],R25) -> 0
K26: =+SUMIFS(DINEROJEFF[Presupuesto],DINEROJEFF[Mes],$B$3,DINEROJEFF[[Descripcion ]],J26) -> 0 | L26: =+SUMIFS(DINEROJEFF[Monto],DINEROJEFF[Mes],$B$3,DINEROJEFF[[Descripcion ]],J26) -> 0 | O26: =+SUMIFS(DINEROJEFF[Presupuesto],DINEROJEFF[Mes],$B$3,DINEROJEFF[[Descripcion ]],N26) -> 0 | P26: =+SUMIFS(DINEROJEFF[Monto],DINEROJEFF[Mes],$B$3,DINEROJEFF[[Descripcion ]],N26) -> 0 | S26: =+SUMIFS(DINEROJEFF[Presupuesto],DINEROJEFF[Mes],$B$3,DINEROJEFF[[Descripcion ]],R26) -> 0 | T26: =+SUMIFS(DINEROJEFF[Monto],DINEROJEFF[Mes],$B$3,DINEROJEFF[[Descripcion ]],R26) -> 0
K27: =+SUMIFS(DINEROJEFF[Presupuesto],DINEROJEFF[Mes],$B$3,DINEROJEFF[[Descripcion ]],J27) -> 0 | L27: =+SUMIFS(DINEROJEFF[Monto],DINEROJEFF[Mes],$B$3,DINEROJEFF[[Descripcion ]],J27) -> 0 | O27: =+SUMIFS(DINEROJEFF[Presupuesto],DINEROJEFF[Mes],$B$3,DINEROJEFF[[Descripcion ]],N27) -> 0 | P27: =+SUMIFS(DINEROJEFF[Monto],DINEROJEFF[Mes],$B$3,DINEROJEFF[[Descripcion ]],N27) -> 0 | S27: =+SUMIFS(DINEROJEFF[Presupuesto],DINEROJEFF[Mes],$B$3,DINEROJEFF[[Descripcion ]],R27) -> 0 | T27: =+SUMIFS(DINEROJEFF[Monto],DINEROJEFF[Mes],$B$3,DINEROJEFF[[Descripcion ]],R27) -> 0
J28: Total | K28: =+SUM(K12:K27) -> 177.5 | L28: =+SUM(L12:L27) -> 7.5 | N28: Total | O28: =+SUM(O12:O27) -> 15 | P28: =+SUM(P12:P27) -> 47 | R28: Total | S28: =+SUM(S22:S27) -> 0 | T28: =+SUM(T22:T27) -> 0

Sheet Presupuesto Anual
A1: Mes | B1: Ingresos | C1: Gastos | D1: Ahorro
A2: Enero
A3: Febrero
A4: Marzo
A5: Abril
A6: Mayo
A7: Junio
A8: Julio
A9: Agosto
A10: Septiembre
A11: Octubre
A12: Noviembre
A13: Diciembre
